odoo/addons/mrp_bom_structure_xlsx_level_1/README.rst
odoo/addons/mrp_bom_structure_xlsx_level_1/__init__.py
odoo/addons/mrp_bom_structure_xlsx_level_1/__manifest__.py
odoo/addons/mrp_bom_structure_xlsx_level_1/i18n/de.po
odoo/addons/mrp_bom_structure_xlsx_level_1/i18n/it.po
odoo/addons/mrp_bom_structure_xlsx_level_1/i18n/mrp_bom_structure_xlsx_level_1.pot
odoo/addons/mrp_bom_structure_xlsx_level_1/readme/CONTRIBUTORS.md
odoo/addons/mrp_bom_structure_xlsx_level_1/readme/DESCRIPTION.md
odoo/addons/mrp_bom_structure_xlsx_level_1/readme/USAGE.md
odoo/addons/mrp_bom_structure_xlsx_level_1/report/__init__.py
odoo/addons/mrp_bom_structure_xlsx_level_1/report/bom_structure_xlsx.py
odoo/addons/mrp_bom_structure_xlsx_level_1/report/bom_structure_xlsx.xml
odoo/addons/mrp_bom_structure_xlsx_level_1/static/description/icon.png
odoo/addons/mrp_bom_structure_xlsx_level_1/static/description/index.html
odoo/addons/mrp_bom_structure_xlsx_level_1/tests/__init__.py
odoo/addons/mrp_bom_structure_xlsx_level_1/tests/test_mrp_bom_structure_xlsx_level_1.py
odoo_addon_mrp_bom_structure_xlsx_level_1-17.0.1.0.0.3.dist-info/METADATA
odoo_addon_mrp_bom_structure_xlsx_level_1-17.0.1.0.0.3.dist-info/WHEEL
odoo_addon_mrp_bom_structure_xlsx_level_1-17.0.1.0.0.3.dist-info/top_level.txt
odoo_addon_mrp_bom_structure_xlsx_level_1-17.0.1.0.0.3.dist-info/RECORD
