Metadata-Version: 2.1
Name: odoo-addon-mrp_bom_structure_xlsx_level_1
Version: 17.0.1.0.0.3
Requires-Python: >=3.10
Requires-Dist: odoo-addon-mrp_bom_structure_xlsx>=17.0dev,<17.1dev
Requires-Dist: odoo>=17.0a,<17.1dev
Summary: Export BOM Structure (Level 1) to Excel .XLSX
Home-page: https://github.com/OCA/manufacture-reporting
License: AGPL-3
Author: ForgeFlow, Odoo Community Association (OCA)
Author-email: support@odoo-community.org
Classifier: Programming Language :: Python
Classifier: Framework :: Odoo
Classifier: Framework :: Odoo :: 17.0
Classifier: License :: OSI Approved :: GNU Affero General Public License v3
